geoio/__init__.py
geoio/_version.py
geoio/base.py
geoio/constants.py
geoio/dg.py
geoio/downsample.py
geoio/downsample_numba.py
geoio/landsat.py
geoio/plotting.py
geoio/utils.py
geoio/tests/__init__.py
geoio/tests/test_downsample.py
geoio/tests/test_geoio_medium.py
geoio/tests/test_geoio_small.py
geoio-1.3.0.data/scripts/find_files.py
geoio-1.3.0.data/scripts/run_spectral_conversions.py
geoio-1.3.0.dist-info/METADATA
geoio-1.3.0.dist-info/RECORD
geoio-1.3.0.dist-info/WHEEL
geoio-1.3.0.dist-info/top_level.txt
