Metadata-Version: 2.1
Name: geoio
Version: 1.3.0
Summary: Geo image reading/writing tools.
Home-page: UNKNOWN
Author: Nathan Longbotham
Author-email: nlongbotham@digitalglobe.com
License: UNKNOWN
Platform: UNKNOWN
Requires-Dist: gdal
Requires-Dist: xmltodict
Requires-Dist: pytz
Requires-Dist: tzwhere
Requires-Dist: ephem
Requires-Dist: numpy
Requires-Dist: tinytools
Requires-Dist: plotly
